[
    {
        "processtime":"2016-12-23 13:19:07",
        "status":"20",
        "stepno":"01",
        "textbody":"医生【双向内审2】在2016-12-23 13:19:07提交了患者【四】的申请"
    },
    {
        "applytime":"2016-12-23 13:19:55.0",
        "processtime":"2016-12-23 13:19:55.0",
        "status":"10",
        "stepno":"02",
        "textbody":"审核医生【铁路采集1】在2016-12-23 13:19:55.0驳回了申请医生【双向内审2】关于患者【四】的申请，驳回原因为【干活吧】。"
    },
    {
        "processtime":"2016-12-23 13:21:16",
        "status":"20",
        "stepno":"03",
        "textbody":"医生【双向内审2】在2016-12-23 13:21:16提交了患者【四】的申请"
    },
    {
        "applytime":"2016-12-23 13:22:51.0",
        "processtime":"2016-12-23 13:22:51.0",
        "status":"10",
        "stepno":"04",
        "textbody":"审核医生【铁路采集1】在2016-12-23 13:22:51.0驳回了申请医生【双向内审2】关于患者【四】的申请，驳回原因为【嘎嘎嘎】。"
    },
    {
        "processtime":"2016-12-23 13:35:23",
        "status":"20",
        "stepno":"05",
        "textbody":"医生【双向内审2】在2016-12-23 13:35:23提交了患者【四】的申请"
    },
    {
        "applytime":"2016-12-23 13:36:54.0",
        "processtime":"2016-12-23 13:36:54.0",
        "status":"10",
        "stepno":"06",
        "textbody":"审核医生【铁路采集1】在2016-12-23 13:36:54.0驳回了申请医生【双向内审2】关于患者【四】的申请，驳回原因为【公关部】。"
    }
]